[
  {
    "id": 12344,
    "title": "Product 1",
    "status": "accepted",
    "displayPicture": "Link",
    "price": 100,
    "date": "12/11/2022, 11:12:52 AM",
    "paymentStatus": "paid",
    "quantity": 2
  },
  {
    "id": 12345,
    "title": "Product 2",
    "status": "pending",
    "displayPicture": "Link",
    "price": 100,
    "date": "11/11/2022, 11:18:52 AM",
    "paymentStatus": "cod",
    "quantity": 2
  },
  {
    "id": 12346,
    "title": "Product 3",
    "status": "shipped",
    "displayPicture": "Link",
    "price": 200,
    "date": "12/11/2022, 11:28:52 AM",
    "paymentStatus": "paid"
  },
  {
    "id": 12347,
    "title": "Product 4",
    "status": "accepted",
    "displayPicture": "Link",
    "price": 700,
    "date": "10/11/2022, 11:38:52 AM",
    "paymentStatus": "cod",
    "quantity": 2
  },
  {
    "id": 12348,
    "title": "Product 5",
    "status": "shipped",
    "displayPicture": "Link",
    "price": 400,
    "date": "12/11/2022, 10:12:52 AM",
    "paymentStatus": "paid",
    "quantity": 2
  }
]
